LICENSE
MANIFEST.in
README.md
setup.py
catapult/__init__.py
catapult/_version.py
catapult/formatters.py
catapult/plugin.py
catapult/result.py
catapult/runner.py
catapult.egg-info/PKG-INFO
catapult.egg-info/SOURCES.txt
catapult.egg-info/dependency_links.txt
catapult.egg-info/entry_points.txt
catapult.egg-info/requires.txt
catapult.egg-info/top_level.txt