Metadata-Version: 1.1
Name: catapult
Version: 0.2.5
Summary: TAP, TAP-J, and TAP-Y output for unittest suites
Home-page: https://github.com/jcelliott/catapult
Author: Joshua C Elliott
Author-email: joshuacelliott@gmail.com
License: MIT
Keywords: TAP TAP-J TAP-Y testing unittest
Platform: UNKNOWN
Classifier: Development Status :: 3 - Alpha
Classifier: Environment :: Console
Classifier: Intended Audience :: Developers
Classifier: License :: OSI Approved :: MIT License
Classifier: Operating System :: OS Independent
Classifier: Programming Language :: Python :: 2.7
Classifier: Topic :: Software Development :: Testing
